examples/__init__.py
examples/allocator.py
examples/barrier.py
examples/child_watcher.py
examples/counter.py
examples/data_watcher.py
examples/double_barrier.py
examples/election.py
examples/lease.py
examples/locking.py
examples/party.py
examples/runtime_config.py
examples/shared_locking.py
examples/transactions.py
zoonado/__init__.py
zoonado/client.py
zoonado/compat.py
zoonado/connection.py
zoonado/encoding.py
zoonado/exc.py
zoonado/features.py
zoonado/iterables.py
zoonado/retry.py
zoonado/session.py
zoonado/states.py
zoonado/transaction.py
zoonado/protocol/__init__.py
zoonado/protocol/acl.py
zoonado/protocol/auth.py
zoonado/protocol/check.py
zoonado/protocol/children.py
zoonado/protocol/close.py
zoonado/protocol/connect.py
zoonado/protocol/create.py
zoonado/protocol/data.py
zoonado/protocol/delete.py
zoonado/protocol/exists.py
zoonado/protocol/part.py
zoonado/protocol/ping.py
zoonado/protocol/primitives.py
zoonado/protocol/reconfig.py
zoonado/protocol/request.py
zoonado/protocol/response.py
zoonado/protocol/sasl.py
zoonado/protocol/stat.py
zoonado/protocol/sync.py
zoonado/protocol/transaction.py
zoonado/protocol/watches.py
zoonado/recipes/__init__.py
zoonado/recipes/allocator.py
zoonado/recipes/barrier.py
zoonado/recipes/base_lock.py
zoonado/recipes/base_watcher.py
zoonado/recipes/children_watcher.py
zoonado/recipes/counter.py
zoonado/recipes/data_watcher.py
zoonado/recipes/double_barrier.py
zoonado/recipes/election.py
zoonado/recipes/lease.py
zoonado/recipes/lock.py
zoonado/recipes/party.py
zoonado/recipes/proxy.py
zoonado/recipes/recipe.py
zoonado/recipes/sequential.py
zoonado/recipes/shared_lock.py
zoonado/recipes/tree_cache.py
zoonado-0.9.2.dist-info/DESCRIPTION.rst
zoonado-0.9.2.dist-info/METADATA
zoonado-0.9.2.dist-info/RECORD
zoonado-0.9.2.dist-info/WHEEL
zoonado-0.9.2.dist-info/entry_points.txt
zoonado-0.9.2.dist-info/metadata.json
zoonado-0.9.2.dist-info/top_level.txt
